{
  "Evidence ID": "E0061",
  "Title": "Access Control & Authorisation Provisions",
  "Description": "",
  "Checksum": "",
  "Timestamp": "",
  "Signed file": "",
  "Evidence Date": "",
  "Evidence Type": "GOV",
  "Evidence Maturity": "Process",
  "Responsible Actor": "Legal Officer",
  "Scope Attribution": "",
  "Architecture-specific": "No",
  "Expected Validation Approach": "Manual Review",
  "Validation Notes": "",
  "Related Requirement ID(s)": [
    "R002"
  ],
  "Related Requirements Summary": [],
  "Notes": ""
}