{
  "Evidence ID": "E0127",
  "Title": "User manual on using software applications and how to use the repository of software packages",
  "Description": "",
  "Checksum": "",
  "Timestamp": "",
  "Signed file": "",
  "Evidence Date": "",
  "Evidence Type": "",
  "Evidence Maturity": "",
  "Responsible Actor": "",
  "Scope Attribution": "",
  "Architecture-specific": "",
  "Expected Validation Approach": "",
  "Validation Notes": "",
  "Related Requirement ID(s)": [
    "R037"
  ],
  "Related Requirements Summary": [],
  "Notes": ""
}